 {
      "id": 0,
      "jobDescription": "string",      
      "dateTime": "2025-07-29T05:16:15.372Z",

      "participants": [
        {
          "id": 0,
          "dateTime": "2025-07-29T05:18:15.372Z",
          "o2": "10",
          "lel": "12",
          "h2sPpm": "42",
	  "nameOfFe": "Field Agent 1" 
        },
        {
          "id": 0,
          "dateTime": "2025-07-29T05:18:15.372Z",
          "o2": "15",
          "lel": "22",
          "h2sPpm": "45",
	  "nameOfFe": "Field Agent 2" 
        }
      ]
    }