 {
      "id": 0,
      "phase": "Phase Dummy",
      "location": "PCMC",
      "dateTime": "2025-07-29T05:16:15.372Z",
      "sign": "string",
      "appendixRequestList": [
        {
          "id": 0,
          "checkListText": "string",
          "requiredAns": "string",
          "actualAns": "Yes"
        },
        {
          "id": 0,
          "checkListText": "string",
          "requiredAns": "string",
          "actualAns": "Yes"
        },
        {
          "id": 0,
          "checkListText": "string",
          "requiredAns": "string",
          "actualAns": "Yes"
        },
        {
          "id": 0,
          "checkListText": "string",
          "requiredAns": "string",
          "actualAns": "Yes"
        }
      ],
      "fieldExecutiveName": "Neo",
      "fieldExecutiveDateTime": "2025-07-30T05:16:15.372Z"
    }